app/__init__.py
app/graphs.py
app/main_window.py
app/profile_manager.py
app/system_utils.py
ryzen_master_commander-0.1.7.dist-info/LICENSE
ryzen_master_commander-0.1.7.dist-info/METADATA
ryzen_master_commander-0.1.7.dist-info/WHEEL
ryzen_master_commander-0.1.7.dist-info/entry_points.txt
ryzen_master_commander-0.1.7.dist-info/top_level.txt
ryzen_master_commander-0.1.7.dist-info/RECORD
